MANIFEST.in
README.md
setup.cfg
setup.py
rdflib_sqlite/SQLite.py
rdflib_sqlite/__init__.py
rdflib_sqlite.egg-info/PKG-INFO
rdflib_sqlite.egg-info/SOURCES.txt
rdflib_sqlite.egg-info/dependency_links.txt
rdflib_sqlite.egg-info/entry_points.txt
rdflib_sqlite.egg-info/requires.txt
rdflib_sqlite.egg-info/top_level.txt
test/__init__.py
test/context_case.py
test/graph_case.py
test/test_core_sqlite.py
test/test_spb2_sparql.py
test/test_sqlite.py
test/test_store_performance.py
test/sp2b/10ktriples.n3
test/sp2b/1ktriples.n3
test/sp2b/25ktriples.n3
test/sp2b/2ktriples.n3
test/sp2b/3ktriples.n3
test/sp2b/500triples.n3
test/sp2b/50ktriples.n3
test/sp2b/5ktriples.n3
test/sp2b/queries/q01.sparql
test/sp2b/queries/q02.sparql
test/sp2b/queries/q03a.sparql
test/sp2b/queries/q03b.sparql
test/sp2b/queries/q03c.sparql
test/sp2b/queries/q04.sparql
test/sp2b/queries/q05a.sparql
test/sp2b/queries/q05b.sparql
test/sp2b/queries/q06.sparql
test/sp2b/queries/q07.sparql
test/sp2b/queries/q08.sparql
test/sp2b/queries/q09.sparql
test/sp2b/queries/q10.sparql
test/sp2b/queries/q11.sparql
test/sp2b/queries/q12a.sparql
test/sp2b/queries/q12b.sparql
test/sp2b/queries/q12c.sparql