Metadata-Version: 1.1
Name: rdflib-sqlite
Version: 0.1
Summary: rdflib extension adding SQLite as back-end store
Home-page: http://github.com/RDFLib/rdflib-sqlite
Author: Graham Higgins
Author-email: gjhiggins@gmail.com
License: BSD
Download-URL: https://github.com/RDFLib/rdflib-sqlite/zipball/master
Platform: any
Classifier: Programming Language :: Python
Classifier: Programming Language :: Python :: 2
Classifier: Programming Language :: Python :: 3
Classifier: Programming Language :: Python :: 2.4
Classifier: Programming Language :: Python :: 2.5
Classifier: Programming Language :: Python :: 2.6
Classifier: Programming Language :: Python :: 2.7
Classifier: Programming Language :: Python :: 3.2
Classifier: License :: OSI Approved :: BSD License
Classifier: Topic :: Software Development :: Libraries :: Python Modules
Classifier: Operating System :: OS Independent
Classifier: Natural Language :: English
